Metadata-Version: 2.1
Name: VkStatusPy
Version: 1.1
Summary: Simple module for easy-working with VK Status
Home-page: UNKNOWN
Author: LeetCrash
Author-email: leetcrash.official@gmail.com
License: UNKNOWN
Platform: UNKNOWN
